firebasil/__init__.py
firebasil/auth/__init__.py
firebasil/auth/auth.py
firebasil/auth/constants.py
firebasil/auth/types.py
firebasil/exceptions.py
firebasil/rtdb.py
firebasil/sse/__init__.py
firebasil/sse/sse_client.py
firebasil/types.py
firebasil/warnings.py
firebasil-0.1.6.dist-info/LICENSE.md
firebasil-0.1.6.dist-info/WHEEL
firebasil-0.1.6.dist-info/METADATA
firebasil-0.1.6.dist-info/RECORD
