Metadata-Version: 2.1
Name: firebasil
Version: 0.1.6
Summary: A modern async Firebase library
Home-page: https://github.com/k2bd/firebasil
License: MIT
Author: Kevin Duff
Author-email: kevinkelduff@gmail.com
Requires-Python: >=3.7,<4.0
Classifier: Development Status :: 1 - Planning
Classifier: Intended Audience :: Developers
Classifier: License :: OSI Approved :: MIT License
Classifier: Operating System :: OS Independent
Classifier: Programming Language :: Python
Classifier: Programming Language :: Python :: 3
Classifier: Programming Language :: Python :: 3 :: Only
Classifier: Programming Language :: Python :: 3.10
Classifier: Programming Language :: Python :: 3.7
Classifier: Programming Language :: Python :: 3.8
Classifier: Programming Language :: Python :: 3.9
Classifier: Topic :: Database
Classifier: Topic :: Software Development :: Libraries
Provides-Extra: docs
Requires-Dist: aiohttp (>=3.8.1,<4.0.0)
Requires-Dist: aiohttp-sse-client (>=0.2.1,<0.3.0)
Requires-Dist: dateparser (>=1.1.0,<2.0.0)
Requires-Dist: stringcase (>=1.2.0,<2.0.0)
Requires-Dist: typing-extensions (>=4.1.1,<5.0.0)
Project-URL: Documentation, https://firebasil.readthedocs.io/
Project-URL: Repository, https://github.com/k2bd/firebasil
